odoo/addons/ssi_general_audit_worksheet_preliminary_materiality/README.rst
odoo/addons/ssi_general_audit_worksheet_preliminary_materiality/__init__.py
odoo/addons/ssi_general_audit_worksheet_preliminary_materiality/__manifest__.py
odoo/addons/ssi_general_audit_worksheet_preliminary_materiality/data/approval_template_data.xml
odoo/addons/ssi_general_audit_worksheet_preliminary_materiality/data/general_audit_worksheet_type_data.xml
odoo/addons/ssi_general_audit_worksheet_preliminary_materiality/data/ir_sequence_data.xml
odoo/addons/ssi_general_audit_worksheet_preliminary_materiality/data/policy_template_data.xml
odoo/addons/ssi_general_audit_worksheet_preliminary_materiality/data/sequence_template_data.xml
odoo/addons/ssi_general_audit_worksheet_preliminary_materiality/models/__init__.py
odoo/addons/ssi_general_audit_worksheet_preliminary_materiality/models/general_audit_ws_6dcda0e.py
odoo/addons/ssi_general_audit_worksheet_preliminary_materiality/models/general_audit_ws_6dcda0e_materiality_mapping.py
odoo/addons/ssi_general_audit_worksheet_preliminary_materiality/models/general_audit_ws_d9d2b44.py
odoo/addons/ssi_general_audit_worksheet_preliminary_materiality/security/ir.model.access.csv
odoo/addons/ssi_general_audit_worksheet_preliminary_materiality/security/ir_module_category_data.xml
odoo/addons/ssi_general_audit_worksheet_preliminary_materiality/security/ir_rule_data.xml
odoo/addons/ssi_general_audit_worksheet_preliminary_materiality/security/res_group_data.xml
odoo/addons/ssi_general_audit_worksheet_preliminary_materiality/static/description/icon.png
odoo/addons/ssi_general_audit_worksheet_preliminary_materiality/views/general_audit_ws_6dcda0e_views.xml
odoo/addons/ssi_general_audit_worksheet_preliminary_materiality/views/general_audit_ws_d9d2b44_views.xml
odoo14_addon_ssi_general_audit_worksheet_preliminary_materiality-14.0.1.0.0.dist-info/METADATA
odoo14_addon_ssi_general_audit_worksheet_preliminary_materiality-14.0.1.0.0.dist-info/WHEEL
odoo14_addon_ssi_general_audit_worksheet_preliminary_materiality-14.0.1.0.0.dist-info/top_level.txt
odoo14_addon_ssi_general_audit_worksheet_preliminary_materiality-14.0.1.0.0.dist-info/RECORD
